[
    {
        "id": "fboard_30728730",
        "category": "인증/후기",
        "title": "도쿄 출장 가서 발견한 힙합의 흔적.jpg",
        "href": "/fboard/30728730",
        "author": "killakim",
        "date": "2025.01.27",
        "commentNum": "18",
        "isVideo": false,
        "isPhoto": true
    },
    {
        "id": "fboard_30723349",
        "category": "리뷰",
        "title": "Jane Remover - Frailty 세계관 / 티저 해석",
        "href": "/fboard/30723349",
        "author": "nettspend",
        "date": "2025.01.26",
        "commentNum": "22",
        "isVideo": true,
        "isPhoto": false
    },
    {
        "id": "fboard_30732689",
        "category": "인증/후기",
        "title": "바이닐 몇 개 인증",
        "href": "/fboard/30732689",
        "author": "앞날",
        "date": "2025.01.27",
        "commentNum": "17",
        "isVideo": false,
        "isPhoto": true
    },
    {
        "id": "fboard_30719139",
        "category": "리뷰",
        "title": "엘이 정상화를 위한 The Life Of Pablo 리뷰",
        "href": "/fboard/30719139",
        "author": "동동e",
        "date": "2025.01.26",
        "commentNum": "24",
        "isVideo": false,
        "isPhoto": true
    },
    {
        "id": "fboard_30725368",
        "category": "그림/아트웍",
        "title": "드레이크 특(만화, 스압)",
        "href": "/fboard/30725368",
        "author": "i$$homan",
        "date": "2025.01.26",
        "commentNum": "51",
        "isVideo": false,
        "isPhoto": true
    },
    {
        "id": "fboard_30719581",
        "category": "인증/후기",
        "title": "JPEGMAFIA - All My Heroes Are Cornballs 바이닐",
        "href": "/fboard/30719581",
        "author": "내눈을녹여미래를보시오",
        "date": "2025.01.26",
        "commentNum": "30",
        "isVideo": true,
        "isPhoto": true
    },
    {
        "id": "fboard_30716462",
        "category": "음악",
        "title": "다음에 해석할 거 공개함.",
        "href": "/fboard/30716462",
        "author": "Mr.SlowFlow",
        "date": "2025.01.26",
        "commentNum": "18",
        "isVideo": false,
        "isPhoto": true
    },
    {
        "id": "fboard_30709669",
        "category": "인증/후기",
        "title": "설 연휴 기념 명반 인증",
        "href": "/fboard/30709669",
        "author": "TagMe",
        "date": "2025.01.25",
        "commentNum": "28",
        "isVideo": false,
        "isPhoto": true
    },
    {
        "id": "fboard_30701208",
        "category": "음악",
        "title": "MIKE - MAY GOD BLESS YOUR HUSTLE 전곡 해석 완료",
        "href": "/fboard/30701208",
        "author": "PDFMAFIA",
        "date": "2025.01.25",
        "commentNum": "15",
        "isVideo": false,
        "isPhoto": true
    },
    {
        "id": "fboard_30709235",
        "category": "음악",
        "title": "크리스 브라운 (2) 아이콘 발매 반대 1일차",
        "href": "/fboard/30709235",
        "author": "아이돈라이크힙합",
        "date": "2025.01.25",
        "commentNum": "15",
        "isVideo": false,
        "isPhoto": true
    },
    {
        "id": "fboard_30704080",
        "category": "인증/후기",
        "title": "이번달에 구한 CD + LP",
        "href": "/fboard/30704080",
        "author": "dDog",
        "date": "2025.01.25",
        "commentNum": "34",
        "isVideo": false,
        "isPhoto": true
    },
    {
        "id": "fboard_30701741",
        "category": "인증/후기",
        "title": "HOUSE OF BALLOONS CD",
        "href": "/fboard/30701741",
        "author": "AbélMakkonenTesfaye",
        "date": "2025.01.25",
        "commentNum": "21",
        "isVideo": true,
        "isPhoto": true
    },
    {
        "id": "fboard_30692571",
        "category": "일반",
        "title": "알라딘에서 명반 발견함",
        "href": "/fboard/30692571",
        "author": "내눈을녹여미래를보시오",
        "date": "2025.01.24",
        "commentNum": "35",
        "isVideo": false,
        "isPhoto": true
    },
    {
        "id": "fboard_30690971",
        "category": "인증/후기",
        "title": "​​​​​​​센치 1회차 개대충평",
        "href": "/fboard/30690971",
        "author": "카티야앨범내",
        "date": "2025.01.24",
        "commentNum": "3",
        "isVideo": false,
        "isPhoto": true
    },
    {
        "id": "fboard_30697294",
        "category": "리뷰",
        "title": "음악충 선정 역사상 가장 위대한 명반 리스트 TOP 101 ~ 150",
        "href": "/fboard/30697294",
        "author": "음충이",
        "date": "2025.01.24",
        "commentNum": "39",
        "isVideo": false,
        "isPhoto": true
    },
    {
        "id": "fboard_30692359",
        "category": "리뷰",
        "title": "제이콜의 'Love Yourz'와 어린왕자",
        "href": "/fboard/30692359",
        "author": "lemonhead",
        "date": "2025.01.24",
        "commentNum": "10",
        "isVideo": true,
        "isPhoto": false
    },
    {
        "id": "fboard_30685384",
        "category": "음악",
        "title": "최근 두달정도 동안 들은 앨범들로 만든 탑스터",
        "href": "/fboard/30685384",
        "author": "lemonhead",
        "date": "2025.01.23",
        "commentNum": "23",
        "isVideo": false,
        "isPhoto": true
    },
    {
        "id": "fboard_30672654",
        "category": "리뷰",
        "title": "THIS IS JPEGMAFIA #3 [완결/스압 주의]",
        "href": "/fboard/30672654",
        "author": "크밍",
        "date": "2025.01.22",
        "commentNum": "10",
        "isVideo": true,
        "isPhoto": true
    },
    {
        "id": "fboard_30687014",
        "category": "일반",
        "title": "가입 기념 탑스터",
        "href": "/fboard/30687014",
        "author": "이스릿",
        "date": "2025.01.23",
        "commentNum": "27",
        "isVideo": false,
        "isPhoto": true
    },
    {
        "id": "fboard_30681867",
        "category": "인증/후기",
        "title": "역대급으로 이쁜 이번달 구매한 바이닐들",
        "href": "/fboard/30681867",
        "author": "6vrter6",
        "date": "2025.01.23",
        "commentNum": "52",
        "isVideo": true,
        "isPhoto": true
    }
]